asc/__init__.py
asc/asc.py
asc/cli.py
asc/data.py
asc/utils.py
asc-0.3.1.dist-info/DESCRIPTION.rst
asc-0.3.1.dist-info/METADATA
asc-0.3.1.dist-info/RECORD
asc-0.3.1.dist-info/WHEEL
asc-0.3.1.dist-info/entry_points.txt
asc-0.3.1.dist-info/metadata.json
asc-0.3.1.dist-info/top_level.txt
